{"generated":"2026-07-14T00:10:27Z","generatedAt":"2026-07-14T00:10:27Z","version":"v1","status":"ok","feed_status":{"fire":"ok","weather":"ok","seismic":"empty"},"totals":{"acres_at_risk_lower_bound":517649.0,"acres_at_risk":517649.0,"facilities_at_risk":0,"visitors_at_risk_annual_proxy":19999413,"visitors_coverage_pct":37.5,"visitors_units_covered":6,"visitors_units_missing":10,"visitors_note":"annual-average proxy, not live; static NPS annual visitation joined by UNIT_CODE · coverage: 6/16 affected units in CSV (37.5%) · missing visitation for: BELA, BISO, CAGR, GAAR, JELA, NATC, SAGU, TONT, VALL, YUCH","active_alerts":{"fire":9,"weather":8,"seismic":0},"affected_units_count":16},"by_bureau":{"NPS":{"acres_at_risk_lower_bound":517649.0,"acres_at_risk":517649.0,"units_affected":16,"visitors_annual_proxy":19999413,"affected_units":[{"unit_code":"GRCA","unit_name":"Grand Canyon National Park","region":"IM","state":"AZ","acres_affected_max":272109.9,"hazards":["fire","weather"]},{"unit_code":"LAKE","unit_name":"Lake Mead National Recreation Area","region":"PW","state":"NV","acres_affected_max":214966.2,"hazards":["weather"]},{"unit_code":"SAGU","unit_name":"Saguaro National Park","region":"IM","state":"AZ","acres_affected_max":24900.6,"hazards":["weather"]},{"unit_code":"YUCH","unit_name":"Yukon-Charley Rivers National Preserve","region":"AK","state":"AK","acres_affected_max":2998.6,"hazards":["fire"]},{"unit_code":"TONT","unit_name":"Tonto National Monument","region":"IM","state":"AZ","acres_affected_max":1121.1,"hazards":["weather"]},{"unit_code":"NATR","unit_name":"Natchez Trace Parkway","region":"SE","state":"MS","acres_affected_max":503.7,"hazards":["weather"]},{"unit_code":"CAGR","unit_name":"Casa Grande Ruins National Monument","region":"IM","state":"AZ","acres_affected_max":475.8,"hazards":["weather"]},{"unit_code":"GAAR","unit_name":"Gates of the Arctic National Park","region":"AK","state":"AK","acres_affected_max":167.1,"hazards":["fire"]},{"unit_code":"BELA","unit_name":"Bering Land Bridge National Preserve","region":"AK","state":"AK","acres_affected_max":153.9,"hazards":["fire"]},{"unit_code":"NATC","unit_name":"Natchez National Historical Park","region":"SE","state":"MS","acres_affected_max":97.9,"hazards":["weather"]},{"unit_code":"OLYM","unit_name":"Olympic National Park","region":"PW","state":"WA","acres_affected_max":68.8,"hazards":["fire"]},{"unit_code":"BISO","unit_name":"Big South Fork National River and Recreation Area","region":"SE","state":"TN","acres_affected_max":43.3,"hazards":["weather"]},{"unit_code":"NOCA","unit_name":"North Cascades National Park","region":"PW","state":"WA","acres_affected_max":22.3,"hazards":["fire"]},{"unit_code":"DENA","unit_name":"Denali National Park","region":"AK","state":"AK","acres_affected_max":10.4,"hazards":["fire"]},{"unit_code":"VALL","unit_name":"Valles Caldera National Preserve","region":"IM","state":"NM","acres_affected_max":6.0,"hazards":["fire"]},{"unit_code":"JELA","unit_name":"Jean Lafitte National Historical Park and Preserve","region":"SE","state":"LA","acres_affected_max":3.4,"hazards":["weather"]}]}},"by_hazard_acres":{"fire":3598.2,"weather":514221.9,"seismic":0},"by_hazard_units_dedup":{"fire":8,"weather":9,"seismic":0},"top_incidents":[{"hazard":"weather","id":"urn:oid:2.49.0.1.840.0.a693cd9b7ecb344ef176de2edc5f497b56947d72.001.1","title":"Flash Flood Warning — Pima, AZ","subtitle":"1 unit(s) · 24,901 ac affected · Severe","tone":"elevated","ts":"2026-07-13T16:54:00-07:00","acres_affected_total":24900.6,"meta_summary":{"severity":"Severe","mag":null,"contained_pct":null,"unit_count":1}},{"hazard":"weather","id":"urn:oid:2.49.0.1.840.0.8e00db056bca498462ee2e57d5abf0ba056218fc.001.1","title":"Flash Flood Warning — Pima, AZ","subtitle":"1 unit(s) · 24,878 ac affected · Severe","tone":"elevated","ts":"2026-07-13T16:07:00-07:00","acres_affected_total":24878.4,"meta_summary":{"severity":"Severe","mag":null,"contained_pct":null,"unit_count":1}},{"hazard":"fire","id":"{BAC795CE-E47B-4DFC-8F94-92A07CA2FAE6}","title":"Kathul (US-AK)","subtitle":"2,999 ac · 0% contained · 1 NPS unit(s) · 2,999 ac on-park","tone":"elevated","ts":"2026-06-30T18:53:04Z","acres_affected_total":2998.6,"meta_summary":{"severity":null,"mag":null,"contained_pct":0.0,"unit_count":1}},{"hazard":"fire","id":"{6B9743D7-B9D5-461D-B381-0C11038C32CA}","title":"Allen (US-AK)","subtitle":"1,691 ac · 0% contained · 1 NPS unit(s) · 167 ac on-park","tone":"elevated","ts":"2026-07-03T17:14:26Z","acres_affected_total":167.1,"meta_summary":{"severity":null,"mag":null,"contained_pct":0.0,"unit_count":1}},{"hazard":"weather","id":"urn:oid:2.49.0.1.840.0.fb675313ec828c280942f78a9973593eaab76e2c.001.1","title":"Flood Warning — Lafayette, LA; Vermilion, LA","subtitle":"1 unit(s) · 3 ac affected · Severe","tone":"elevated","ts":"2026-07-13T10:04:00-05:00","acres_affected_total":3.4,"meta_summary":{"severity":"Severe","mag":null,"contained_pct":null,"unit_count":1}},{"hazard":"weather","id":"urn:oid:2.49.0.1.840.0.fcfdef78937dd0f2c845c4b5d4cf75b966206b97.001.1","title":"Severe Thunderstorm Warning — Pinal, AZ","subtitle":"1 unit(s) · 1 ac affected · Severe","tone":"elevated","ts":"2026-07-13T17:09:00-07:00","acres_affected_total":0.5,"meta_summary":{"severity":"Severe","mag":null,"contained_pct":null,"unit_count":1}},{"hazard":"weather","id":"urn:oid:2.49.0.1.840.0.1284846220a0d8248e1bedae5af2298ae21380f5.001.1","title":"Special Weather Statement — Rio Verde/Salt River; East Valley; Fountain Hills/East Mesa; Southeast Valley/Queen Creek; Superior; Northwest Pinal County; West Pinal County; Apache Junction/Gold Canyon; Tonto Basin; Mazatzal Mountains; Pinal/Superstition Mountains; San Carlos; Dripping Springs; Globe/Miami; Southeast Gila County","subtitle":"2 unit(s) · 1,597 ac affected · Moderate","tone":"moderate","ts":"2026-07-13T17:01:00-07:00","acres_affected_total":1596.8,"meta_summary":{"severity":"Moderate","mag":null,"contained_pct":null,"unit_count":2}},{"hazard":"fire","id":"{9115BBB2-E0ED-49E7-946A-7A7E6E4B7541}","title":"Bonanza (US-AK)","subtitle":"427 ac · 0% contained · 1 NPS unit(s) · 427 ac on-park","tone":"moderate","ts":"2026-06-27T17:25:10Z","acres_affected_total":427.2,"meta_summary":{"severity":null,"mag":null,"contained_pct":0.0,"unit_count":1}},{"hazard":"fire","id":"{8A73E623-6A18-47D2-B977-F95E30BACEC8}","title":"Cliff Spring (US-AZ)","subtitle":"171 ac · 0% contained · 1 NPS unit(s) · 171 ac on-park","tone":"moderate","ts":"2026-06-29T21:43:22Z","acres_affected_total":171.1,"meta_summary":{"severity":null,"mag":null,"contained_pct":0.0,"unit_count":1}},{"hazard":"fire","id":"{718E2031-E249-4CD7-A9D1-A76B5D5622F1}","title":"Blueberry (US-AK)","subtitle":"154 ac · 0% contained · 1 NPS unit(s) · 154 ac on-park","tone":"moderate","ts":"2026-07-09T15:32:10Z","acres_affected_total":153.9,"meta_summary":{"severity":null,"mag":null,"contained_pct":0.0,"unit_count":1}}],"stale_hazards":[],"sources":{"fire":"NIFC WFIGS Current Perimeters","weather":"NOAA NWS active alerts (api.weather.gov)","seismic":"USGS Earthquake Hazards Program","lands_mask":"prometheus-doi-lands-data / NPS Land Resources Division"},"notes":{"acres_at_risk_semantics":"acres_at_risk = sum(max acres per unit) — a LOWER BOUND on the true geometric union of hazard fragments. True union is a Phase-2 refinement; the lower bound never over-counts.","hazard_dedup":"per-hazard acres deduplicated by unit_code within a hazard"},"attribution":"PROMETHEUS · DOI Emergency Management · 2026-07-14T00:10:27Z"}